helloww/__init__.py
helloww/helloww.py
helloww-0.0.1.dist-info/METADATA
helloww-0.0.1.dist-info/WHEEL
helloww-0.0.1.dist-info/top_level.txt
helloww-0.0.1.dist-info/RECORD
