Metadata-Version: 2.1
Name: helloww
Version: 0.0.1
Summary: helloww
Home-page: https://github.com/nevergiveupzsj/maxtest
Author: Sun bz
License: MIT
Platform: UNKNOWN
Requires-Python: >=3.6.0
Requires-Dist: numpy
Requires-Dist: matplotlib
Requires-Dist: pandas
Requires-Dist: polygon
Requires-Dist: sqlalchemy
